onepassword_sdk-0.3.2.data/purelib/onepassword/__init__.py
onepassword_sdk-0.3.2.data/purelib/onepassword/build_number.py
onepassword_sdk-0.3.2.data/purelib/onepassword/client.py
onepassword_sdk-0.3.2.data/purelib/onepassword/core.py
onepassword_sdk-0.3.2.data/purelib/onepassword/defaults.py
onepassword_sdk-0.3.2.data/purelib/onepassword/errors.py
onepassword_sdk-0.3.2.data/purelib/onepassword/items.py
onepassword_sdk-0.3.2.data/purelib/onepassword/items_files.py
onepassword_sdk-0.3.2.data/purelib/onepassword/items_shares.py
onepassword_sdk-0.3.2.data/purelib/onepassword/secrets.py
onepassword_sdk-0.3.2.data/purelib/onepassword/test_client.py
onepassword_sdk-0.3.2.data/purelib/onepassword/types.py
onepassword_sdk-0.3.2.data/purelib/onepassword/vaults.py
onepassword_sdk-0.3.2.data/purelib/onepassword/lib/aarch64/libop_uniffi_core.so
onepassword_sdk-0.3.2.data/purelib/onepassword/lib/aarch64/op_uniffi_core.py
onepassword_sdk-0.3.2.dist-info/METADATA
onepassword_sdk-0.3.2.dist-info/WHEEL
onepassword_sdk-0.3.2.dist-info/top_level.txt
onepassword_sdk-0.3.2.dist-info/RECORD
